idlelib/__init__.pyi
idlelib/autocomplete.pyi
idlelib/autocomplete_w.pyi
idlelib/autoexpand.pyi
idlelib/browser.pyi
idlelib/calltip.pyi
idlelib/calltip_w.pyi
idlelib/codecontext.pyi
idlelib/colorizer.pyi
idlelib/config.pyi
idlelib/config_key.pyi
idlelib/configdialog.pyi
idlelib/debugger.pyi
idlelib/debugger_r.pyi
idlelib/debugobj.pyi
idlelib/debugobj_r.pyi
idlelib/delegator.pyi
idlelib/dynoption.pyi
idlelib/editor.pyi
idlelib/filelist.pyi
idlelib/format.pyi
idlelib/grep.pyi
idlelib/help.pyi
idlelib/help_about.pyi
idlelib/history.pyi
idlelib/hyperparser.pyi
idlelib/idle.pyi
idlelib/iomenu.pyi
idlelib/macosx.pyi
idlelib/mainmenu.pyi
idlelib/multicall.pyi
idlelib/outwin.pyi
idlelib/parenmatch.pyi
idlelib/pathbrowser.pyi
idlelib/percolator.pyi
idlelib/py.typed
idlelib/pyparse.pyi
idlelib/pyshell.pyi
idlelib/query.pyi
idlelib/redirector.pyi
idlelib/replace.pyi
idlelib/rpc.pyi
idlelib/run.pyi
idlelib/runscript.pyi
idlelib/scrolledlist.pyi
idlelib/search.pyi
idlelib/searchbase.pyi
idlelib/searchengine.pyi
idlelib/sidebar.pyi
idlelib/squeezer.pyi
idlelib/stackviewer.pyi
idlelib/statusbar.pyi
idlelib/textview.pyi
idlelib/tooltip.pyi
idlelib/tree.pyi
idlelib/undo.pyi
idlelib/util.pyi
idlelib/window.pyi
idlelib/zoomheight.pyi
idlelib/zzdummy.pyi
types_idlelib-0.0.0.dist-info/licenses/LICENSE
types_idlelib-0.0.0.dist-info/METADATA
types_idlelib-0.0.0.dist-info/WHEEL
types_idlelib-0.0.0.dist-info/top_level.txt
types_idlelib-0.0.0.dist-info/RECORD
