Metadata-Version: 2.4
Name: types-idlelib
Version: 0.0.0
Summary: Typing stubs for the stdlib idlelib module
Author-email: CoolCat467 <CoolCat467@duck.com>
License-Expression: MIT
Project-URL: Source, https://github.com/CoolCat467/types-idlelib
Project-URL: Bug Tracker, https://github.com/CoolCat467/types-idlelib/issues
Classifier: Development Status :: 4 - Beta
Classifier: Intended Audience :: Developers
Classifier: Natural Language :: English
Classifier: Programming Language :: Python :: 3
Classifier: Programming Language :: Python :: 3.9
Classifier: Programming Language :: Python :: 3.10
Classifier: Programming Language :: Python :: 3.11
Classifier: Programming Language :: Python :: 3.12
Classifier: Programming Language :: Python :: 3.13
Classifier: Programming Language :: Python :: 3 :: Only
Classifier: Topic :: Software Development
Classifier: Topic :: Text Editors :: Integrated Development Environments (IDE)
Classifier: Operating System :: OS Independent
Classifier: Framework :: IDLE
Classifier: Typing :: Typed
Requires-Python: >=3.9
License-File: LICENSE
Provides-Extra: tools
Requires-Dist: uv>=0.5.21; extra == "tools"
Requires-Dist: ruff>=0.9.2; extra == "tools"
Requires-Dist: pre-commit>=4.2.0; extra == "tools"
Requires-Dist: attrs>=25.3.0; extra == "tools"
Requires-Dist: mypy>=1.17.0; extra == "tools"
Dynamic: license-file
